openg2p_g2p_bridge_api/__init__.py
openg2p_g2p_bridge_api/app.py
openg2p_g2p_bridge_api/celery_app.py
openg2p_g2p_bridge_api/config.py
openg2p_g2p_bridge_api/controllers/__init__.py
openg2p_g2p_bridge_api/controllers/account_statement.py
openg2p_g2p_bridge_api/controllers/benefit_program_configuration.py
openg2p_g2p_bridge_api/controllers/disbursement.py
openg2p_g2p_bridge_api/controllers/disbursement_envelope.py
openg2p_g2p_bridge_api/controllers/disbursement_envelope_status.py
openg2p_g2p_bridge_api/controllers/disbursement_status.py
openg2p_g2p_bridge_api/services/__init__.py
openg2p_g2p_bridge_api/services/account_statement.py
openg2p_g2p_bridge_api/services/benefit_program_configuration.py
openg2p_g2p_bridge_api/services/disbursement.py
openg2p_g2p_bridge_api/services/disbursement_envelope.py
openg2p_g2p_bridge_api/services/disbursement_envelope_status.py
openg2p_g2p_bridge_api/services/disbursement_status.py
openg2p_g2p_bridge_api/services/request_validations.py
openg2p_g2p_bridge_api/utils/__init__.py
openg2p_g2p_bridge_api-1.1.0.dist-info/METADATA
openg2p_g2p_bridge_api-1.1.0.dist-info/WHEEL
openg2p_g2p_bridge_api-1.1.0.dist-info/RECORD
